adt7422/__init__.py
adt7422/adt7422.py
adt7422-1.0.3.dist-info/LICENSE
adt7422-1.0.3.dist-info/METADATA
adt7422-1.0.3.dist-info/WHEEL
adt7422-1.0.3.dist-info/top_level.txt
adt7422-1.0.3.dist-info/RECORD
