Metadata-Version: 2.1
Name: adt7422
Version: 1.0.3
Summary: adt7422 quick start with Raspberry Pi computers
Home-page: https://github.com/ievgenrai/ADT7422-Temperature-sensor
Author: Ievgen Raievskiy
Author-email: 
License: MIT
Keywords: example python
Platform: UNKNOWN
Classifier: Development Status :: 4 - Beta
Classifier: Topic :: Utilities
Classifier: License :: OSI Approved :: MIT License
Classifier: Programming Language :: Python :: 3.7
Classifier: License :: OSI Approved :: MIT License
Classifier: Operating System :: OS Independent
Requires-Python: >=3.7
